DESCRIPTION.rst
MANIFEST.in
README.md
setup.cfg
setup.py
dcpy/__init__.py
dcpy/widget.py
dcpy.egg-info/PKG-INFO
dcpy.egg-info/SOURCES.txt
dcpy.egg-info/dependency_links.txt
dcpy.egg-info/top_level.txt