Metadata-Version: 1.2
Name: dcpy
Version: 0.1.9
Summary: This is an easy yet powerful python library for interactive data visualization and analysis using dcjs and crossfilter.
Home-page: https://github.com/washim/dcpy
Author: Washim Ahmed
Author-email: info@washimahmed.com
License: UNKNOWN
Keywords: visualization,d3,crossfilter,dc
Platform: UNKNOWN
Classifier: Development Status :: 3 - Alpha
Classifier: Intended Audience :: Developers
Classifier: License :: OSI Approved :: MIT License
Classifier: Programming Language :: Python :: 3.6
Requires-Python: >=3
